lysergic/__init__.py
lysergic/lysergic.py
lysergic/test_lysergic.py
lysergic-0.1.5.dist-info/LICENSE
lysergic-0.1.5.dist-info/METADATA
lysergic-0.1.5.dist-info/WHEEL
lysergic-0.1.5.dist-info/entry_points.txt
lysergic-0.1.5.dist-info/top_level.txt
lysergic-0.1.5.dist-info/RECORD
